openstar/__init__.py
openstar/main.py
openstar-0.0.0.dist-info/LICENSE
openstar-0.0.0.dist-info/METADATA
openstar-0.0.0.dist-info/WHEEL
openstar-0.0.0.dist-info/top_level.txt
openstar-0.0.0.dist-info/RECORD
